<?xml version="1.0" encoding="UTF-8" ?>
<activity xmlns:xi="http://www.w3.org/2001/XInclude" xml:id="act-7-3-1">
<statement>
<p>Consider the initial value problem
      <me>
        \frac{dy}{dt} = 2t-1, \ y(0) = 0
      </me>

      <ol label="a">
        <li><p>Use Euler's method with <m>\Delta t = 0.2</m> to approximate the solution
            at <m>t_i = 0.2, 0.4, 0.6, 0.8</m>, and <m>1.0</m>.   Record your work in the following table, and sketch the points <m>(t_i,
            y_i)</m> on the axes provided.
        <sidebyside>    
            <table width="50%" xml:id="T-act-7-3-1">
            <tabular>
              <row bottom="minor">
                <cell></cell>
                <cell></cell>
                <cell></cell>
                <cell></cell>
                <cell></cell>
              </row>
              <row>
                <cell><m>t_i</m></cell>
                <cell><m>y_i</m></cell>
                <cell><m>dy/dt <fillin characters="10" /></m> </cell>
                <cell><m>\Delta y</m></cell>
              </row>
              <row bottom="medium">
                <cell></cell>
                <cell></cell>
                <cell></cell>
                <cell></cell>
                <cell></cell>
              </row>
              <row>
                <cell>0.0000</cell>
                <cell>0.0000</cell>
                <cell></cell>
                <cell></cell>
              </row>
              <row bottom="minor">
                <cell></cell>
                <cell></cell>
                <cell></cell>
                <cell></cell>
                <cell></cell>
              </row>
              <row>
                <cell>0.2000</cell>
                <cell></cell>
                <cell></cell>
                <cell></cell>
              </row>
              <row bottom="minor">
                <cell></cell>
                <cell></cell>
                <cell></cell>
                <cell></cell>
                <cell></cell>
              </row>
              <row>
                <cell>0.4000</cell>
                <cell></cell>
                <cell></cell>
                <cell></cell>
              </row>
              <row bottom="minor">
                <cell></cell>
                <cell></cell>
                <cell></cell>
                <cell></cell>
                <cell></cell>
              </row>
              <row>
                <cell>0.6000</cell>
                <cell></cell>
                <cell></cell>
                <cell></cell>
              </row>
              <row bottom="minor">
                <cell></cell>
                <cell></cell>
                <cell></cell>
                <cell></cell>
                <cell></cell>
              </row>
              <row>
                <cell>0.8000</cell>
                <cell></cell>
                <cell></cell>
                <cell></cell>
              </row>
              <row bottom="minor">
                <cell></cell>
                <cell></cell>
                <cell></cell>
                <cell></cell>
                <cell></cell>
              </row>
              <row>
                <cell>1.0000</cell>
                <cell></cell>
                <cell></cell>
                <cell></cell>
              </row>
              <row bottom="minor">
                <cell></cell>
                <cell></cell>
                <cell></cell>
                <cell></cell>
                <cell></cell>
              </row>
            </tabular>
            </table>
            <figure width="50%" xml:id="F-act-7-3-1-grid">
                <image width="90%" source="images/7_3_euler_empty" />
            </figure>
        </sidebyside>        
          </p></li>

        <li><p>Find the exact solution to the original initial value problem
              and use this function to find the error in your approximation at each one of the points
              <m>t_i</m>.</p></li>

        <li><p>Explain why the value <m>y_5</m> generated by Euler's method for this initial value problem
              produces the same value as a left Riemann sum for the definite integral <m>\int_0^1
              (2t-1)~dt</m>.</p></li>

        <li><p>How would your computations differ if the initial value was <m>y(0) =
              1</m>?  What does this mean about different solutions to this
              differential equation?</p></li>
      </ol>
      </p>

</statement>
      <hint>
        <p>

        <ol label="a">
          <li><p>Small hints for each of the prompts above.</p></li>
        </ol>
        </p>
      </hint>

      <answer>
        <p>

        <ol label="a">
          <li><p>Solutions for each of the prompts above.</p></li>
        </ol>
        </p>
      </answer>
      
      <solution>
        <p>

        <ol label="a">
          <li><p>Solutions for each of the prompts above.</p></li>
        </ol>
        </p>
      </solution>
    </activity>    

