<?xml version="1.0" encoding="UTF-8" ?>
<activity xmlns:xi="http://www.w3.org/2001/XInclude" xml:id="act-5-5-2">
<statement>
<p>For each of the following integrals, evaluate the integral using <m>u</m>-substitution and/or an entry from the table found in <xref ref="integral-table">Appendix</xref>.

      <ol label="a." cols="2">
        <li><p><m>\int \sqrt{x^2 + 4} \, dx</m></p></li>

        <li><p><m>\int \frac{x}{\sqrt{x^2 +4}} \, dx</m></p></li>

        <li><p><m>\int \frac{2}{\sqrt{16+25x^2}}\, dx</m></p></li>

        <li><p><m>\int \frac{1}{x^2 \sqrt{49-36x^2}} \, dx</m></p></li>
      </ol>
      </p>

</statement>
      <hint>
        <p>
        <ol label="a.">
          <li><p>Compare <m>\int \sqrt{u^2 + a^2} \, du</m>.</p></li>
          <li><p>Try a straightforward <m>u</m>-substitution; the table is unneeded.</p></li>
          <li><p>Let <m>a = 4</m> and <m>u = 5x</m> and look for a similar integral in the table.</p></li>
          <li><p>Let <m>a = 7</m> and <m>u = 6x</m>; find a related integral in the table.</p></li>
        </ol>
        </p>
      </hint>

      <answer>
        <p>
        <ol label="a.">
          <li>
           <p>
            <m>\int \sqrt{x^2 + 4} \, dx = \frac{1}{2} \arctan(\frac{x}{2})+C.</m>
           </p></li>
          <li>
           <p>
            <m>\int \frac{x}{\sqrt{x^2 +4}} \, dx = \sqrt{x^2 + 4} + C.</m>
          </p></li>
          <li><p>
            <m>\int \frac{2}{\sqrt{16+25x^2}}\, dx = \frac{2}{5} \ln| 5x + \sqrt{16+25x^2} | + C.</m>
            </p></li>
            <li><p>
              <m>\int \frac{1}{x^2 \sqrt{49-36x^2}} \, dx = - \frac{\sqrt{49-36x^2}}{49x} + C.</m>
            </p></li>
        </ol>
        </p>
      </answer>

      <solution>
        <p>
        <ol label="a.">
          <li><p>By (1) in <xref ref="integral-table">Appendix</xref> with <m>a=2</m> and <m>u = x</m>,
            <me>\int \sqrt{x^2 + 4} \, dx = \frac{1}{2} \arctan(\frac{x}{2})+C.</me>
           </p></li>
          <li><p>Let <m>u=x^2 + 4</m>, so <m>du = 2x dx</m>.  Thus
            <me>\int \frac{x}{\sqrt{x^2 +4}} \, dx = \frac{1}{2} \int \frac{du}{\sqrt{u}} = \frac{1}{2} \cdot 2u^{1/2} + C = \sqrt{x^2 + 4} + C.</me>
          </p></li>
          <li><p>Letting <m>a = 4</m> and <m>u = 5x</m>, we see <m>du=5dx</m>.  Thus,
            <me>\int \frac{2}{\sqrt{16+25x^2}}\, dx = \frac{2}{5} \int \frac{du}{\sqrt{a^2 + u^2}.</me>
            Now by (2) in <xref ref="integral-table">Appendix</xref>, it follows
            <me>\int \frac{2}{\sqrt{16+25x^2}}\, dx = \frac{2}{5} \ln| 5x + \sqrt{16+25x^2} | + C.</me>
            </p></li>
            <li><p>Letting <m>a = 7</m> and <m>u = 6x</m>, it follows <m>x=\frac{1}{6}u</m> and <m>du=6dx</m>, and therefore
              <me>\int \frac{1}{x^2 \sqrt{49-36x^2}} \, dx = \frac{1}{6} \int \frac{1}{\frac{1}{36}u^2 \sqrt{a^2-u^2}} \, du.</me>
              Using (11) in <xref ref="integral-table">Appendix</xref> and the fact that <m>\frac{1}{6} \cdot 36 = 6</m>, we see
              <me>\int \frac{1}{x^2 \sqrt{49-36x^2}} \, dx = -6\cdot \frac{\sqrt{49-36x^2}}{49 \cdot 6x} + C.</me>
            </p></li>
        </ol>
        </p>
      </solution>
    </activity>
