<?xml version="1.0" encoding="UTF-8" ?>
<!-- **********************************************************************-->
<!-- Copyright 2012-2018                                                   -->
<!-- Matthew Boelkins                                                      -->
<!--                                                                       -->
<!-- This file is part of Active Calculus.                                 -->
<!--                                                                       -->
<!-- Permission is granted to copy, distribute and/or modify this document -->
<!-- under the terms of the Creative Commons BY-SA license.  The work      -->
<!-- may be used for free by any party so long as attribution is given to  -->
<!-- the author(s), the work and its derivatives are used in the spirit of -->
<!-- "share and share alike".  All trademarks are the registered marks of  -->
<!-- their respective owners.                                              -->
<!-- **********************************************************************-->
<activity xmlns:xi="http://www.w3.org/2001/XInclude" xml:id="act-1-8-1" permid="cIn">
  <statement>
    <p permid="EfD">
      Suppose it is known that for a given differentiable function <m>y = g(x)</m>,
      its local linearization at the point where <m>a = -1</m> is given by <m>L(x) = -2 + 3(x+1)</m>.

      <ol label="a." permid="wWD">
        <li permid="ddM">
          <p permid="UtU">
            Compute the values of <m>L(-1)</m> and <m>L'(-1)</m>.
          </p>
        </li>

        <li permid="JkV">
          <p permid="ABd">
            What must be the values of <m>g(-1)</m> and <m>g'(-1)</m>?
            Why?
          </p>
        </li>

        <li permid="pse">
          <p permid="gIm">
            Do you expect the value of
            <m>g(-1.03)</m> to be greater than or less than the value of <m>g(-1)</m>?
            Why?
          </p>
        </li>

        <li permid="Vzn">
          <p permid="MPv">
            Use the local linearization to estimate the value of <m>g(-1.03)</m>.
          </p>
        </li>

        <li permid="BGw">
          <p permid="sWE">
            Suppose that you also know that <m>g''(-1) = 2</m>.
            What does this tell you about the graph of <m>y = g(x)</m> at <m>a = -1</m>?
          </p>
        </li>

        <li permid="hNF">
          <p permid="ZdN">
            For <m>x</m> near <m>-1</m>,
            sketch the graph of the local linearization
            <m>y = L(x)</m> as well as a possible graph of
            <m>y = g(x)</m> on the axes provided in <xref ref="F-1-8-Act1">Figure</xref>.
          </p>
        </li>
      </ol>
    </p>

    <figure xml:id="F-1-8-Act1" permid="kmM">
      <caption>Axes for plotting <m>y = L(x)</m> and <m>y = g(x)</m>.</caption>
      <image width="47%" source="images/1_8_Act1" />
    </figure>
  </statement>
  <hint permid="YtT">
    <p permid="XYu">
      <ol label="a." permid="QPu">
        <li permid="NUO">
          <p permid="FkW">
            Follow the rule for <m>L</m>.
          </p>
        </li>

        <li permid="ubX">
          <p permid="lsf">
            Recall that the form of the local linearization is <m>L(x) = g(a) + g'(a)(x-a)</m>.
          </p>
        </li>

        <li permid="ajg">
          <p permid="Rzo">
            Is the function <m>g</m> increasing or decreasing at <m>a = -1</m>?
          </p>
        </li>

        <li permid="Gqp">
          <p permid="xGx">
            Remember that <m>g(-1.03) \approx L(-1.03)</m>.
          </p>
        </li>

        <li permid="mxy">
          <p permid="dNG">
            What does the second derivative tell you about the shape of a curve?
          </p>
        </li>

        <li permid="SEH">
          <p permid="JUP">
            Use your work above.
          </p>
        </li>
      </ol>
    </p>
  </hint>
  <answer permid="smK">
    <p permid="rRl">
      <ol label="a." permid="kIl">
        <li permid="yLQ">
          <p permid="qbY">
            <m>L(-1) = -2</m>; <m>L'(-1) = 3</m>.
          </p>
        </li>

        <li permid="eSZ">
          <p permid="Wjh">
            <m>g(-1) = -2</m>; <m>g'(-1) = 3</m>.
          </p>
        </li>

        <li permid="Lai">
          <p permid="Cqq">
            Less.
          </p>
        </li>

        <li permid="rhr">
          <p permid="ixz">
            <m>g(-1.03) \approx L(-1.03) = -2.09</m>.
          </p>
        </li>

        <li permid="XoA">
          <p permid="OEI">
            Concave up.
          </p>
        </li>

        <li permid="DvJ">
          <p permid="uLR">
            The illustration below shows a possible graph of <m>y = g(x)</m> near <m>x = -1</m>,
            along with the tangent line
            <m>y = L(x)</m> through <m>(-1, g(-1))</m>.
          </p>

          <sidebyside width="50%" permid="QtV">
            <image source="images/1_8_Act1Soln" />
          </sidebyside>

        </li>
      </ol>
    </p>
  </answer>
  <solution permid="MfB">
    <p permid="LKc">
      <ol label="a." permid="EBc">
        <li permid="jCS">
          <p permid="aTa">
            Using the formula for <m>L</m>,
            <m>L(-1) = -2</m>; Since
            <m>L'(x) = 3</m>, we see <m>L'(-1) = 3</m>.
          </p>
        </li>

        <li permid="PKb">
          <p permid="Haj">
            Since <m>L(x) = g(-1) + g'(-1)(x+1) = -2 + 3(x+1)</m>,
            we see <m>g(-1) = -2</m> and <m>g'(-1) = 3</m>.
            Alternatively,
            we could observe that the value and slope of <m>g</m> must match the value and slope of <m>L</m> at the point of tangency.
          </p>
        </li>

        <li permid="vRk">
          <p permid="nhs">
            Because <m>g'(-1) = 3</m>,
            we see that <m>g'</m> is increasing near <m>a = -1</m>, and therefore <m>g(-1.03)</m> is expected to be less than <m>g(-1)</m>.
          </p>
        </li>

        <li permid="bYt">
          <p permid="ToB">
            Observe that <m>g(-1.03) \approx L(-1.03) = -2 + 3(-1.03+1) = -2 - 0.09 = -2.09</m>.
          </p>
        </li>

        <li permid="IfC">
          <p permid="zvK">
            Since <m>g''(-1) > 0</m>,
            we know <m>g</m> is concave up at <m>x = -1</m>.
          </p>
        </li>

        <li permid="omL">
          <p permid="fCT">
            In the figure below,
            we use the results of our previous work to generate the plot shown,
            which is a possible graph of <m>y = g(x)</m> near <m>x = -1</m>,
            along with the tangent line
            <m>y = L(x)</m> through <m>(-1, g(-1))</m>.
          </p>

          <sidebyside widths="100%" permid="wBe">
            <image source="images/1_8_Act1Soln" />
          </sidebyside>

        </li>
      </ol>
    </p>
  </solution>
</activity>

