<?xml version="1.0" encoding="UTF-8" ?>
<!-- **********************************************************************-->
<!-- Copyright 2012-2018                                                   -->
<!-- Matthew Boelkins                                                      -->
<!--                                                                       -->
<!-- This file is part of Active Calculus.                                 -->
<!--                                                                       -->
<!-- Permission is granted to copy, distribute and/or modify this document -->
<!-- under the terms of the Creative Commons BY-SA license.  The work      -->
<!-- may be used for free by any party so long as attribution is given to  -->
<!-- the author(s), the work and its derivatives are used in the spirit of -->
<!-- "share and share alike".  All trademarks are the registered marks of  -->
<!-- their respective owners.                                              -->
<!-- **********************************************************************-->
<exercises xmlns:xi="http://www.w3.org/2001/XInclude" xml:id="ez-2-6" permid="YSJ">

  <exercise xml:id="ez-2-6-WW1" permid="Cmq">
    <title>Composite function involving logarithms and polynomials</title>
    <webwork source="Library/Michigan/Chap3Sec6/Q01.pg" />
  </exercise>

  <exercise xml:id="ez-2-6-WW2" permid="itz">
    <title>Composite function involving trigonometric functions and logarithms</title>
    <webwork source="Library/Michigan/Chap3Sec6/Q19.pg" />
  </exercise>

  <exercise xml:id="ez-2-6-WW3" permid="OAI">
    <title>Product involving <m>\arcsin(w)</m></title>
    <webwork source="Library/Michigan/Chap3Sec6/Q21.pg" />
  </exercise>

  <exercise xml:id="ez-2-6-WW4" permid="uHR">
    <title>Derivative involving <m>\arctan(x)</m></title>
    <webwork source="Library/Michigan/Chap3Sec6/Q45.pg" />
  </exercise>

  <exercise xml:id="ez-2-6-WW5" permid="aPa">
    <title>Composite function from a graph</title>
    <webwork source="Library/Michigan/Chap3Sec6/Q51.pg" />
  </exercise>

  <exercise xml:id="ez-2-6-WW6" permid="GWj">
    <title>Composite function involving an inverse trigonometric function</title>
    <webwork source="Library/Rochester/setDerivatives6InverseTrig/sc3_6_25.pg" />
  </exercise>

  <exercise xml:id="ez-2-6-WW7" permid="nds">
    <title>Mixing rules: product, chain, and inverse trig</title>
    <webwork source="Library/Rochester/setDerivatives6InverseTrig/sc3_6_26.pg" />
  </exercise>

  <exercise xml:id="ez-2-6-WW8" permid="TkB">
    <title>Mixing rules: product and inverse trig</title>
    <webwork source="Library/Rochester/setDerivatives6InverseTrig/sc3_6_32a.pg" />
  </exercise>
  <!-- Uses EV2, not compatible with PTX -->
  <!--
  <exercise xml:id="ez-2-6-WW9">
    <webwork source="Library/Rochester/setDerivatives7Log/mec4.pg" />
  </exercise>
  -->
  <exercise permid="zrK">
    <statement>
      <p permid="KPe">
        Determine the derivative of each of the following functions.
        Use proper notation and clearly identify the derivative rules you use.

        <ol label="a." permid="ymr">
          <li permid="qHS">
            <p permid="wbF">
              <m>f(x) = \ln(2\arctan(x) + 3\arcsin(x) + 5)</m>
            </p>
          </li>

          <li permid="WPb">
            <p permid="ciO">
              <m>r(z) = \arctan(\ln(\arcsin(z)))</m>
            </p>
          </li>

          <li permid="CWk">
            <p permid="IpX">
              <m>q(t) = \arctan^2(3t) \arcsin^4(7t)</m>
            </p>
          </li>

          <li permid="jdt">
            <p permid="oxg">
              <m>g(v) = \ln\left( \frac{\arctan(v)}{\arcsin(v) + v^2} \right)</m>
            </p>
          </li>
        </ol>
      </p>
    </statement>
    <answer permid="EbD">
      <p permid="tQT">
        <ol label="a." permid="tCy">
          <li permid="PkC">
            <p permid="UEp">
              <m>
              f'(x) = \frac{1}{2\arctan(x) + 3\arcsin(x) + 5} \cdot \left(\frac{2}{1+x^2} + \frac{3}{\sqrt{1-x^2}}\right)</m>.
            </p>
          </li>

          <li permid="vrL">
            <p permid="ALy">
              <m>
              r'(z) = \frac{1}{1+\left(\ln(\arcsin(z))\right)^2} \cdot \left( \frac{1}{\arcsin(z)} \right) \cdot \frac{1}{\sqrt{1-z^2}}</m>.
            </p>
          </li>

          <li permid="byU">
            <p permid="gSH">
              <m>
              q'(t) = \arctan^2(3t) \cdot \left[4\arcsin^3(7t) \left( \frac{7}{\sqrt{1-(7t)^2}} \right)\right] + \arcsin^4(7t) \cdot \left[2\arctan(3t) \left(\frac{3}{1+(3t)^2}\right) \right]</m>.
            </p>
          </li>

          <li permid="HGd">
            <p permid="MZQ">
              <m>
              g'(v) = \frac{1}{\frac{\arctan(v)}{\arcsin(v) + v^2}} \cdot \frac{(\arcsin(v) + v^2) \cdot \frac{1}{1+v^2} - \arctan(v) \cdot \left(\frac{1}{\sqrt{1-v^2}} + 2v \right)}{(\arcsin(v) + v^2)^2} 
              </m>
            </p>
          </li>
        </ol>
      </p>
    </answer>
    <solution permid="XUu">
      <p permid="Voj">
        <ol label="a." permid="UZO">
          <li permid="nNm">
            <p permid="tgZ">
              By the chain rule,
              <me permid="jrO">
                f'(x) = \frac{1}{2\arctan(x) + 3\arcsin(x) + 5} \cdot \frac{d}{dx}\left( 2\arctan(x) + 3\arcsin(x) + 5\right)
              </me>,
              and by the sum and constant multiple rules, it follows that
              <me permid="PyX">
                f'(x) = \frac{1}{2\arctan(x) + 3\arcsin(x) + 5} \cdot \left(\frac{2}{1+x^2} + \frac{3}{\sqrt{1-x^2}}\right)
              </me>.
            </p>
          </li>

          <li permid="TUv">
            <p permid="Zoi">
              By the chain rule applied to the outermost function,
              <me permid="vGg">
                r'(z) = \frac{1}{1+\left(\ln(\arcsin(z))\right)^2} \cdot \frac{d}{dz} \left( \ln(\arcsin(z)) \right)
              </me>.
              Applying the chain rule again to evaluate <m>\frac{d}{dz} \left( \ln(\arcsin(z)) \right)</m>,
              <me permid="bNp">
                r'(z) = \frac{1}{1+\left(\ln(\arcsin(z))\right)^2} \cdot \left( \frac{1}{\arcsin(z)} \right) \cdot \frac{d}{dz}\left(\arcsin(z)\right)
              </me>.
              Finally, using the basic rule for <m>\frac{d}{dz}\left(\arcsin(z)\right)</m>,
              <me permid="HUy">
                r'(z) = \frac{1}{1+\left(\ln(\arcsin(z))\right)^2} \cdot \left( \frac{1}{\arcsin(z)} \right) \cdot \frac{1}{\sqrt{1-z^2}}
              </me>.
            </p>
          </li>

          <li permid="AbE">
            <p permid="Fvr">
              First, by the product rule,
              <me permid="obH">
                q'(t) = \arctan^2(3t) \cdot \frac{d}{dt}\left(\arcsin^4(7t)\right) +  \arcsin^4(7t) \cdot \frac{d}{dt}\left(\arctan^2(3t)\right)
              </me>.
              Next, we recall that <m>\arcsin^4(7t) = \left(\arcsin(7t)\right)^4</m> and <m>\arctan^2(3t) = \left( \arctan(3t) \right)^2</m>,
              and apply the chain rule to find the derivative of each of these functions to get
              <me permid="UiQ">
                q'(t) = \arctan^2(3t) \cdot \left[4\arcsin^3(7t) \frac{d}{dt}\left( \arcsin(7t) \right)\right] +  \arcsin^4(7t) \cdot \left[2\arctan(3t) \frac{d}{dt}\left(\arctan(3t)\right) \right] 
              </me>.
              Finally, applying the chain rule one more time to evaluate the remaining derivatives,
              <me permid="ApZ">
                q'(t) = \arctan^2(3t) \cdot \left[4\arcsin^3(7t) \left( \frac{7}{\sqrt{1-(7t)^2}} \right)\right] +  \arcsin^4(7t) \cdot \left[2\arctan(3t) \left(\frac{3}{1+(3t)^2}\right) \right]
              </me>.
            </p>
          </li>

          <li permid="giN">
            <p permid="lCA">
              By the chain rule,
              <me permid="gxi">
                g'(v) = \frac{1}{ \frac{\arctan(v)}{\arcsin(v) + v^2} } \cdot \frac{d}{dv}\left[ \frac{\arctan(v)}{\arcsin(v) + v^2} \right]
              </me>
              Thus, by the quotient rule,
              <me permid="MEr">
                g'(v) = \frac{1}{\frac{\arctan(v)}{\arcsin(v) + v^2}} \cdot \frac{(\arcsin(v) + v^2) \cdot \frac{1}{1+v^2} - \arctan(v) \cdot \left(\frac{1}{\sqrt{1-v^2}} + 2v \right)}{(\arcsin(v) + v^2)^2}
              </me>
            </p>
          </li>
        </ol>
      </p>
    </solution>
  </exercise>

  <exercise xml:id="ez-2-6-Ez4" permid="fyT">
    <statement>
      <p permid="qWn">
        Consider the graph of <m>y = f(x)</m> provided in <xref ref="F-2-6-Ez4">Figure</xref>
        and use it to answer the following questions.
      </p>

      <sidebyside widths="47% 47%" margins="0%" permid="JQP">
        <p permid="yAM">
          <ol label="a." permid="Sfi">
            <li permid="MpW">
              <p permid="RJJ">
                Use the provided graph to estimate the value of <m>f'(1)</m>.
              </p>
            </li>

            <li permid="sxf">
              <p permid="xQS">
                Sketch an approximate graph of <m>y = f^{-1}(x)</m>.
                Label at least three distinct points on the graph that correspond to three points on the graph of <m>f</m>.
              </p>
            </li>

            <li permid="YEo">
              <p permid="dYb">
                Based on your work in (a),
                what is the value of <m>(f^{-1})'(-1)</m>?
                Why?
              </p>
            </li>
          </ol>
        </p>

        <figure xml:id="F-2-6-Ez4" permid="eHV">
          <caption>A function <m>y = f(x)</m></caption>
          <image source="images/2_6_Ez4" />
        </figure>
      </sidebyside>
    </statement>
    <answer permid="QpV">
      <p permid="ZYc">
        <ol label="a." permid="ZJH">
          <li permid="ELx">
            <p permid="Kfk">
              <m>f'(1) \approx 2</m>.
            </p>
          </li>

          <li permid="kSG">

            <sidebyside width="50%" permid="pXY">
              <image source="images/2_6_Ez4Soln" />
            </sidebyside>

          </li>

          <li permid="QZP">
            <p permid="qmt">
              <m>(f^{-1})'(-1) \approx 1/2</m>.
            </p>
          </li>
        </ol>
      </p>
    </answer>
    <solution permid="kiM">
      <p permid="Bvs">
        <ol label="a." permid="BgX">
          <li permid="xgY">
            <p permid="WtC">
              By plotting the tangent line as shown in the figure below,
              it appears that <m>f'(1) \approx 2</m>.
            </p>
          </li>

          <li permid="doh">
            <p permid="CAL">
              One way to estimate the graph of
              <m>y = f^{-1}(x)</m> is to plot several <m>(x,y)</m> points on the graph of
              <m>y = f(x)</m> and then plot the corresponding points <m>(y,x)</m> with the coordinates reversed.
              Doing so and recalling that the graph of
              <m>y = f^{-1}(x)</m> is the reflection of the graph of
              <m>y = f(x)</m> across the line <m>y = x</m>,
              we see the following figure.
            </p>

            <sidebyside width="50%" permid="Wfh">
              <image source="images/2_6_Ez4Soln" />
            </sidebyside>

          </li>

          <li permid="Jvq">
            <p permid="iHU">
              Because the original function passes through the point <m>(1,-1)</m>,
              the inverse function passes through <m>(-1,1)</m>.
              Moreover, since the tangent line to the original function at <m>(1,-1)</m> has slope <m>f'(1) \approx 2</m>,
              and the tangent line to the inverse function at <m>(-1,1)</m> corresponds to the reflection of the original tangent line across the line <m>y=x</m>,
              it follows that <m>(f^{-1})'(-1) \approx 1/2</m>.
              This can also be deduced from the ``derivative of an inverse function'' rule,
              whereby <m>(f^{-1})'(-1) = \frac{1}{f'(1)}</m>.
            </p>
          </li>
        </ol>
      </p>
    </solution>
  </exercise>

  <exercise permid="LGc">
    <statement>
      <p permid="Xdw">
        Let <m>f(x) = \frac{1}{4}x^3 + 4</m>.

        <ol label="a." permid="etA">
          <li permid="pCz">
            <p permid="OPd">
              Sketch a graph of <m>y = f(x)</m> and explain why <m>f</m> is an invertible function.
            </p>
          </li>

          <li permid="VJI">
            <p permid="uWm">
              Let <m>g</m> be the inverse of <m>f</m> and determine a formula for <m>g</m>.
            </p>
          </li>

          <li permid="BQR">
            <p permid="bdv">
              Compute <m>f'(x)</m>, <m>g'(x)</m>,
              <m>f'(2)</m>, and <m>g'(6)</m>.
              What is the special relationship between <m>f'(2)</m> and <m>g'(6)</m>?
              Why?
            </p>
          </li>
        </ol>
      </p>
    </statement>
    <answer permid="cEn">
      <p permid="Gfl">
        <ol label="a." permid="FQQ">
          <li permid="hYa">
            <p permid="HkE">
              <m>f</m> passes the horizontal line test.
            </p>
          </li>

          <li permid="Ofj">
            <p permid="nrN">
              <m>f^{-1}(x) = g(x) = \sqrt[3]{4x-16}</m>.
            </p>
          </li>

          <li permid="ums">
            <p permid="TyW">
              <m>f'(x) = \frac{3}{4}x^2</m>;
              <m>f'(2) = 3</m>. <m>g'(x) = \frac{1}{3}(4x-16)^{-2/3} \cdot 4</m>;
              <m>g'(6) = \frac{1}{3}</m>.
              These two derivative values are reciprocals.
            </p>
          </li>
        </ol>
      </p>
    </answer>
    <solution permid="wxe">
      <p permid="hCB">
        <ol label="a." permid="hog">
          <li permid="atB">
            <p permid="zGf">
              <m>f</m> is an invertible function because its graph passes the horizontal line test.
            </p>
          </li>

          <li permid="GAK">
            <p permid="fNo">
              To find a formula for <m>g = f^{-1}</m>,
              we take the equation <m>y = \frac{1}{4}x^3 + 4</m> and solve for <m>x</m> in terms of <m>y</m>.
              Doing so, we find that <m>y - 4 = \frac{1}{4}x^3</m>,
              so <m>x^3 = 4(y-4)</m>, and thus
              <me permid="sLA">
                x = \sqrt[3]{4(y-4)} = f^{-1}(y)
              </me>.
              Writing the inverse as a function of <m>x</m>,
              we have found that <m>f^{-1}(x) = g(x) = \sqrt[3]{4x-16}</m>.
            </p>
          </li>

          <li permid="mHT">
            <p permid="LUx">
              First, <m>f'(x) = \frac{3}{4}x^2</m>,
              and thus <m>f'(2) = 3</m>.
              Next, <m>g'(x) = \frac{1}{3}(4x-16)^{-2/3} \cdot 4</m>,
              so that <m>g'(6) = \frac{1}{3} \cdot 8^{-2/3} \cdot 4 = \frac{1}{3} \cdot \frac{1}{4} \cdot 4 = \frac{1}{3}</m>.
              What is special about these two derivative values is that they happen to be reciprocals.

              Noting that <m>f(2) = 3</m> and <m>g(3) = 2</m>,
              we know that <m>g'(3) = \frac{1}{f'(2)}</m> by the rule for the derivative of an inverse function,
              and this matches our finding above that <m>g'(3) = \frac{1}{3}</m>.
            </p>
          </li>
        </ol>
      </p>
    </solution>
  </exercise>

  <exercise permid="rNl">
    <statement>
      <p permid="DkF">
        Let <m>h(x) = x + \sin(x)</m>.

        <ol label="a." permid="KAJ">
          <li permid="SPc">
            <p permid="sbG">
              Sketch a graph of <m>y = h(x)</m> and explain why <m>h</m> must be invertible.
            </p>
          </li>

          <li permid="yWl">
            <p permid="YiP">
              Explain why it does not appear to be algebraically possible to determine a formula for <m>h^{-1}</m>.
            </p>
          </li>

          <li permid="fdu">
            <p permid="EpY">
              Observe that the point
              <m>(\frac{\pi}{2}, \frac{\pi}{2} + 1)</m> lies on the graph of <m>y = h(x)</m>.
              Determine the value of <m>(h^{-1})'(\frac{\pi}{2} + 1)</m>.
            </p>
          </li>
        </ol>
      </p>
    </statement>
    <answer permid="oSF">
      <p permid="mmu">
        <ol label="a." permid="lXZ">
          <li permid="LkD">
            <p permid="kxh">
              <m>h</m> passes the horizontal line test.
            </p>
          </li>

          <li permid="rrM">
            <p permid="QEq">
              The equation <m>y = x + \sin(x)</m> can't be solved for <m>x</m> in terms of <m>y</m>.
            </p>
          </li>

          <li permid="XyV">
            <p permid="wLz">
              <m>(h^{-1})'(\frac{\pi}{2} + 1) = 1</m>.
            </p>
          </li>
        </ol>
      </p>
    </answer>
    <solution permid="ILw">
      <p permid="NJK">
        <ol label="a." permid="Nvp">
          <li permid="DGe">
            <p permid="cSI">
              The function <m>h</m> is invertible because its graph passes the horizontal line test.
            </p>
          </li>

          <li permid="jNn">
            <p permid="IZR">
              It does not seem possible to solve the equation
              <m>y = x + \sin(x)</m> for <m>x</m> in terms of <m>y</m>.
            </p>
          </li>

          <li permid="PUw">
            <p permid="pha">
              By the rule for the derivative of an invertible function,
              we have <m>(h^{-1})'(\frac{\pi}{2} + 1) = \frac{1}{h'\left(\frac{\pi}{2} \right)}</m>.
              Thus, we first compute <m>h'(x)</m> and find that <m>h'(x) = 1 + \cos(x)</m>.
              Since <m>h'\left(\frac{\pi}{2} \right) = 1 + \cos\left(\frac{\pi}{2} \right) = 1</m>,
              it follows that <m>(h^{-1})'(\frac{\pi}{2} + 1) = \frac{1}{1} = 1</m>.
            </p>
          </li>
        </ol>
      </p>
    </solution>
  </exercise>

</exercises>
